api_abc_123/__init__.py
api_abc_123/api_save.py
api_abc_123/api_view.py
api_abc_123-1.0.4.dist-info/LICENSE
api_abc_123-1.0.4.dist-info/METADATA
api_abc_123-1.0.4.dist-info/WHEEL
api_abc_123-1.0.4.dist-info/top_level.txt
api_abc_123-1.0.4.dist-info/RECORD
